libname/Akash_102203102.py
libname/__init__.py
topsis_Akash-1.0.0.dist-info/LICENSE
topsis_Akash-1.0.0.dist-info/METADATA
topsis_Akash-1.0.0.dist-info/WHEEL
topsis_Akash-1.0.0.dist-info/top_level.txt
topsis_Akash-1.0.0.dist-info/RECORD
